[
  {
    "img": "https://anasbex-dev.github.io/aka-me/akadata/images/ilust1.webp",
    "title": "Anime Illustration",
    "tag": "Illustration"
  },
  {
    "img": "https://i.ibb.co.com/rK5Jqrf3/1627596405-picsay-01-picsay.jpg",
    "title": "Landscape Illustration",
    "tag": "Illustration"
  },
  {
    "img": "https://i.ibb.co.com/1Y7z3VFG/IMG-20210908-175431.jpg",
    "title": "Landscape photos during cloudy weather",
    "tag": "Photography"
  },
  {
    "img": "https://i.ibb.co.com/tTWjbMq3/IMG-20210813-132039.jpg",
    "title": "Photos with Light Objects ",
    "tag": "Photography"
  }
]